CMakeLists.txt
MANIFEST.in
setup.cfg
setup.py
GIFT_Grab.egg-info/PKG-INFO
GIFT_Grab.egg-info/SOURCES.txt
GIFT_Grab.egg-info/dependency_links.txt
GIFT_Grab.egg-info/entry_points.txt
GIFT_Grab.egg-info/top_level.txt
api/broadcastdaemon.cpp
api/broadcastdaemon.h
api/codec.h
api/device.h
api/except.cpp
api/except.h
api/iobservable.cpp
api/iobservable.h
api/iobserver.h
api/ivideosource.h
api/ivideotarget.h
api/maskframe.cpp
api/maskframe.h
api/videoframe.cpp
api/videoframe.h
api/videosourcefactory.cpp
api/videosourcefactory.h
api/videotargetfactory.cpp
api/videotargetfactory.h
blackmagicsdk/blackmagicsdk_video_source.cpp
blackmagicsdk/blackmagicsdk_video_source.h
blackmagicsdk/deck_link_display_mode_detector.cpp
blackmagicsdk/deck_link_display_mode_detector.h
cmake/GiftGrabConfig.cmake
cmake/blackmagicsdk/CMakeLists.txt
cmake/boost.python/CMakeLists.txt
cmake/cpp11/CMakeLists.txt
cmake/epiphansdk/CMakeLists.txt
cmake/ffmpeg/CMakeLists.txt
cmake/ffmpeg/FindFFmpeg.cmake
cmake/libvlc/CMakeLists.txt
cmake/libvlc/FindLIBVLC.cmake
cmake/libvlc/FindLIBVLC.cmake.LICENSE
cmake/opencv/CMakeLists.txt
cmake/platform/CMakeLists.txt
cmake/pythonlibs/CMakeLists.txt
epiphansdk/epiphansdk_video_source.cpp
epiphansdk/epiphansdk_video_source.h
ffmpeg/ffmpeg_video_source.cpp
ffmpeg/ffmpeg_video_source.h
ffmpeg/ffmpeg_video_target.cpp
ffmpeg/ffmpeg_video_target.h
opencv/opencv_video_source.cpp
opencv/opencv_video_source.h
opencv/opencv_video_target.cpp
opencv/opencv_video_target.h
pip/long_description.rst
python/gil.h
python/wrapper.cpp
python/modules/giftgrab/__init__.py
python/modules/giftgrab/__init__.pyc
python/modules/giftgrab/epiphan.py
python/modules/giftgrab/utils/__init__.py
python/modules/giftgrab/utils/__init__.pyc
python/modules/giftgrab/utils/inspection.py
python/modules/giftgrab/utils/inspection.pyc
tests/CMakeLists.txt
tests/__init__.py
tests/include_catch.h
tests/utils.py
tests/utils.pyc
tests/__pycache__/moduledz.cpython-35.pyc
tests/__pycache__/utils.cpython-35.pyc
tests/blackmagic/decklinksdi4k/CMakeLists.txt
tests/blackmagic/decklinksdi4k/conftest.py
tests/blackmagic/decklinksdi4k/test_observer.py
