Metadata-Version: 1.1
Name: GIFT-Grab
Version: 1708.post1
Summary: A C++ and NumPy-compatible Python API for acquiring, processing and encoding video streams in real time
Home-page: https://github.com/gift-surg/GIFT-Grab
Author: Dzhoshkun Ismail Shakir
Author-email: d.shakir@ucl.ac.uk
License: BSD-3-Clause
Keywords: multi-channel,video capture,real-time video encoding,video processing,hardware-accelerated video encoding,GPU,frame-grabber hardware,network video streaming,Epiphan DVI2PCIe Duo,Blackmagic DeckLink SDI 4K,Epiphan Pearl,Xvid,H.265,H265,VP9,HEVC,C++,Python,NumPy,SciPy,GIFT-Surg
Platform: UNKNOWN
Classifier: Development Status :: 4 - Beta
Classifier: Intended Audience :: Developers
Classifier: Intended Audience :: End Users/Desktop
Classifier: Intended Audience :: Healthcare Industry
Classifier: Intended Audience :: Information Technology
Classifier: Intended Audience :: Science/Research
Classifier: License :: OSI Approved :: BSD License
Classifier: Operating System :: POSIX :: Linux
Classifier: Programming Language :: C++
Classifier: Programming Language :: Python
Classifier: Topic :: Multimedia :: Video
Classifier: Topic :: Multimedia :: Video :: Capture
Classifier: Topic :: Multimedia :: Video :: Conversion
Classifier: Topic :: Scientific/Engineering
Classifier: Topic :: Software Development :: Libraries :: Python Modules
Classifier: Topic :: Utilities
